djangoql/__init__.py
djangoql/admin.py
djangoql/ast.py
djangoql/compat.py
djangoql/exceptions.py
djangoql/lexer.py
djangoql/parser.py
djangoql/parsetab.py
djangoql/queryset.py
djangoql/schema.py
djangoql/serializers.py
djangoql/views.py
djangoql/static/djangoql/css/completion.css
djangoql/static/djangoql/css/completion_admin.css
djangoql/static/djangoql/css/syntax_help.css
djangoql/static/djangoql/img/completion_example.png
djangoql/static/djangoql/img/completion_example_scaled.png
djangoql/static/djangoql/js/completion.js
djangoql/static/djangoql/js/completion_admin.js
djangoql/static/djangoql/js/completion_admin_toggle.js
djangoql/static/djangoql/js/completion_admin_toggle_off.js
djangoql/templates/djangoql/error_message.html
djangoql/templates/djangoql/syntax_help.html
djangoql-0.15.3.dist-info/LICENSE
djangoql-0.15.3.dist-info/METADATA
djangoql-0.15.3.dist-info/WHEEL
djangoql-0.15.3.dist-info/top_level.txt
djangoql-0.15.3.dist-info/RECORD
