Metadata-Version: 2.1
Name: djangoql
Version: 0.15.3
Summary: DjangoQL: Advanced search language for Django
Home-page: https://github.com/ivelum/djangoql/
Author: Denis Stebunov
Author-email: support@ivelum.com
License: MIT License
Platform: UNKNOWN
Classifier: Development Status :: 4 - Beta
Classifier: Intended Audience :: Developers
Classifier: Natural Language :: English
Classifier: License :: OSI Approved :: MIT License
Classifier: Programming Language :: Python
Classifier: Programming Language :: Python :: 2.7
Classifier: Programming Language :: Python :: 3.5
Classifier: Programming Language :: Python :: 3.6
Classifier: Programming Language :: Python :: 3.7
Classifier: Programming Language :: Python :: 3.8
Classifier: Programming Language :: Python :: 3.9
Requires-Dist: ply (>=3.8)
